{
    "visible_tags": [
        "Cryptography",
        "JavaScript",
        "Vue.js",
        "Web",
        "PHP"
    ],
    "projects":[
        {
            "name": "ExplainRSA",
            "icon": "<i class=\"far fa-lock-alt fa-fw\"></i>",
            "description": "An interactive demonstration of RSA.",
            "links":{
                "Website":"https://rsa.iamoctopus.co/",
                "Github":"https://github.com/freddinator/explainrsa"
            },
            "tags": [
                "Cryptography",
                "JavaScript",
                "Vue.js"
            ]
        },
        {
            "name": "Insult",
            "icon": "<span class=\"fa-layers fa-fw\"><i class=\"far fa-comment\"></i><i class=\"fas fa-exclamation\" data-fa-transform=\"shrink-10 up-.5\"></i></span>",
            "description": "A Shakesperian insult generator.",
            "links":{
                "Website":"https://insult.iamoctopus.co/",
                "Github":"https://github.com/freddinator/insult"
            },
            "tags": [
                "Web",
                "PHP"
            ]
        },
        {
            "name": "Fine Brothers Idea Generator",
            "icon": "<i class=\"fab fa-youtube fa-fw\"></i>",
            "description":"Revolutionary money-making ideas.",
            "links":{
                "Website":"https://fine.iamoctopus.co/",
                "Github":"https://github.com/freddinator/fine"
            },
            "tags": [
                "Web",
                "JavaScript"
            ]
        },
        {
            "name": "TR-8R SPIN",
            "icon": "<i class=\"far fa-star fa-fw\"></i>",
            "description":"TRAITOR!",
            "links":{
                "Website":"http://tr-8rspin.com/"
            },
            "tags": [
                "Web",
                "JavaScript"
            ]
        },
    ]
}